ipyvuedraggable/Draggable.py
ipyvuedraggable/__init__.py
ipyvuedraggable/_version.py
ipyvuedraggable-1.1.0.data/data/etc/jupyter/nbconfig/notebook.d/jupyter-vuedraggable.json
ipyvuedraggable-1.1.0.data/data/share/jupyter/labextensions/jupyter-vuedraggable/package.json
ipyvuedraggable-1.1.0.data/data/share/jupyter/labextensions/jupyter-vuedraggable/static/33.3d1065360306ad48deb1.js
ipyvuedraggable-1.1.0.data/data/share/jupyter/labextensions/jupyter-vuedraggable/static/399.b844142923197b209f6b.js
ipyvuedraggable-1.1.0.data/data/share/jupyter/labextensions/jupyter-vuedraggable/static/685.4c2354ee29554480f780.js
ipyvuedraggable-1.1.0.data/data/share/jupyter/labextensions/jupyter-vuedraggable/static/685.4c2354ee29554480f780.js.LICENSE.txt
ipyvuedraggable-1.1.0.data/data/share/jupyter/labextensions/jupyter-vuedraggable/static/remoteEntry.3f122ed6ec4fc75a52d3.js
ipyvuedraggable-1.1.0.data/data/share/jupyter/labextensions/jupyter-vuedraggable/static/style.js
ipyvuedraggable-1.1.0.data/data/share/jupyter/labextensions/jupyter-vuedraggable/static/third-party-licenses.json
ipyvuedraggable-1.1.0.data/data/share/jupyter/nbextensions/jupyter-vuedraggable/extension.js
ipyvuedraggable-1.1.0.data/data/share/jupyter/nbextensions/jupyter-vuedraggable/index.js
ipyvuedraggable-1.1.0.data/data/share/jupyter/nbextensions/jupyter-vuedraggable/index.js.map
ipyvuedraggable-1.1.0.dist-info/LICENSE
ipyvuedraggable-1.1.0.dist-info/METADATA
ipyvuedraggable-1.1.0.dist-info/WHEEL
ipyvuedraggable-1.1.0.dist-info/top_level.txt
ipyvuedraggable-1.1.0.dist-info/RECORD
