Metadata-Version: 2.1
Name: ipyvuedraggable
Version: 1.1.0
Summary: Jupyter widget for Vue.Draggable
Home-page: https://github.com/mariobuikhuizen/ipyvuedraggable
Author: Mario Buikhuizen, Maarten Breddels
Author-email: mbuikhuizen@gmail.com, maartenbreddels@gmail.com
Keywords: ipython,jupyter,widgets
Classifier: Development Status :: 4 - Beta
Classifier: Framework :: IPython
Classifier: Intended Audience :: Developers
Classifier: Intended Audience :: Science/Research
Classifier: Topic :: Multimedia :: Graphics
Classifier: Programming Language :: Python :: 2
Classifier: Programming Language :: Python :: 2.7
Classifier: Programming Language :: Python :: 3
Classifier: Programming Language :: Python :: 3.3
Classifier: Programming Language :: Python :: 3.4
Classifier: Programming Language :: Python :: 3.5
Classifier: Programming Language :: Python :: 3.6
License-File: LICENSE
Requires-Dist: ipyvue<2,>=1.0.0
